README.md
setup.py
proxyaudit/__init__.py
proxyaudit/proxyaudit.py
proxyaudit.egg-info/PKG-INFO
proxyaudit.egg-info/SOURCES.txt
proxyaudit.egg-info/dependency_links.txt
proxyaudit.egg-info/requires.txt
proxyaudit.egg-info/top_level.txt