Metadata-Version: 2.1
Name: proxyaudit
Version: 0.4
Summary: A package to fetch and check the working HTTP,HTTPS,SOCKS4,SOCKS5 proxies from a list of proxies
Home-page: https://github.com/aryanyk/proxyaudit
Author: Aryan Khandhadiya
Author-email: aryanyk562@gmail.com
Classifier: Programming Language :: Python :: 3
Classifier: License :: OSI Approved :: MIT License
Classifier: Operating System :: OS Independent
Requires-Python: >=3.6
Requires-Dist: asyncio
Requires-Dist: aiohttp
Requires-Dist: urllib3
